{
  "trending_topics": [
    {
      "topic": "전기차 충전사업",
      "summary": "전기차 충전사업자 대부분이 충전기 제조사 관련 계열사이며, 충전사업자의 필요성에 대한 논의가 진행 중이다.",
      "post_count": 3,
      "sentiment": "neutral",
      "urgency": "medium"
    },
    {
      "topic": "AI 기술",
      "summary": "AI 기술의 발전과 그에 따른 다양한 산업에서의 적용이 논의되고 있다.",
      "post_count": 10,
      "sentiment": "positive",
      "urgency": "high"
    },
    {
      "topic": "정치 및 사회",
      "summary": "정치 및 사회 관련된 다양한 주제들이 논의되고 있다.",
      "post_count": 15,
      "sentiment": "mixed",
      "urgency": "high"
    }
  ],
  "keywords": [
    {
      "keyword": "전기차",
      "count": 5,
      "sentiment": "neutral",
      "context": "전기차 충전사업과 관련된 키워드"
    },
    {
      "keyword": "AI",
      "count": 10,
      "sentiment": "positive",
      "context": "AI 기술과 그에 따른 산업에서의 적용"
    },
    {
      "keyword": "정치",
      "count": 8,
      "sentiment": "mixed",
      "context": "정치 및 사회 관련된 키워드"
    }
  ],
  "sentiment_overview": {
    "positive": 20,
    "negative": 10,
    "neutral": 30,
    "overall_mood": "중립적인 분위기"
  },
  "business_insights": [
    {
      "insight": "전기차 충전사업의 성장",
      "action": "전기차 충전사업에 대한 투자와 참여",
      "priority": "medium"
    },
    {
      "insight": "AI 기술의 발전",
      "action": "AI 기술의 연구와 개발",
      "priority": "high"
    },
    {
      "insight": "정치 및 사회의 변화",
      "action": "정치 및 사회의 변화에 대한 대응",
      "priority": "high"
    }
  ],
  "narrative": "최근의 트렌드와 키워드를 분석한 결과, 전기차 충전사업과 AI 기술이 주요한 주제로 나타났습니다. 또한, 정치 및 사회 관련된 주제들이 논의되고 있습니다. 이러한 트렌드와 키워드를 통해 사업적인 인사이트를 얻을 수 있으며, 전기차 충전사업과 AI 기술의 성장을 위한 투자와 연구가 필요합니다. 또한, 정치 및 사회의 변화에 대한 대응이 필요합니다.",
  "analyzed_at": "2026-04-10T04:30:33.484Z",
  "post_count": 62,
  "sources": [
    "ppomppu",
    "clien"
  ]
}