{
  "trending_topics": [
    {
      "topic": "이란과 미국의 갈등",
      "summary": "이란과 미국의 갈등이 고조되고 있으며, 이에 따른 전쟁 가능성과 경제적 영향에 대한 논의가 활발하다.",
      "post_count": 10,
      "sentiment": "negative",
      "urgency": "high"
    },
    {
      "topic": "경제 및 금융",
      "summary": "미국과 한국의 경제 및 금융 뉴스에 대한 논의가 많으며, 주택담보대출과 모기지 금리에 대한 우려가 있다.",
      "post_count": 15,
      "sentiment": "neutral",
      "urgency": "medium"
    },
    {
      "topic": "기술 및 IT",
      "summary": "최신 기술 및 IT 뉴스에 대한 논의가 많으며, AI와 전기차에 대한 관심이 높다.",
      "post_count": 12,
      "sentiment": "positive",
      "urgency": "low"
    }
  ],
  "keywords": [
    {
      "keyword": "이란",
      "count": 8,
      "sentiment": "negative",
      "context": "이란과 미국의 갈등"
    },
    {
      "keyword": "미국",
      "count": 10,
      "sentiment": "neutral",
      "context": "미국 경제 및 정치"
    },
    {
      "keyword": "AI",
      "count": 5,
      "sentiment": "positive",
      "context": "최신 기술 및 IT"
    }
  ],
  "sentiment_overview": {
    "positive": 20,
    "negative": 30,
    "neutral": 50,
    "overall_mood": "중립적"
  },
  "business_insights": [
    {
      "insight": "이란과 미국의 갈등이 고조되면 경제에 부정적인 영향을 미칠 수 있다.",
      "action": "경제 및 금융 뉴스를 주시하고 대비책을 마련한다.",
      "priority": "high"
    },
    {
      "insight": "최신 기술 및 IT 뉴스에 대한 관심이 높아지고 있다.",
      "action": "최신 기술 및 IT 뉴스를 주시하고 투자 기회를 찾는다.",
      "priority": "medium"
    }
  ],
  "narrative": "현재 이란과 미국의 갈등이 고조되고 있으며, 이에 따른 전쟁 가능성과 경제적 영향에 대한 논의가 활발하다. 또한, 미국과 한국의 경제 및 금융 뉴스에 대한 논의가 많으며, 주택담보대출과 모기지 금리에 대한 우려가 있다. 최신 기술 및 IT 뉴스에 대한 논의도 많으며, AI와 전기차에 대한 관심이 높다. 따라서, 경제 및 금융 뉴스를 주시하고 대비책을 마련하며, 최신 기술 및 IT 뉴스를 주시하고 투자 기회를 찾는 것이 중요하다.",
  "analyzed_at": "2026-04-01T20:30:34.135Z",
  "post_count": 62,
  "sources": [
    "ppomppu",
    "clien"
  ]
}