{
  "trending_topics": [
    {
      "topic": "정치",
      "summary": "이재명 방북 비용과 관련된 논란, 검찰의 수사와 관련된 뉴스",
      "post_count": 5,
      "sentiment": "negative",
      "urgency": "high"
    },
    {
      "topic": "기술",
      "summary": "신한카드의 애플페이 연동과 관련된 뉴스, 애플의 차단 모드 사용 중 스파이웨어 해킹 사례",
      "post_count": 4,
      "sentiment": "neutral",
      "urgency": "medium"
    },
    {
      "topic": "경제",
      "summary": "국내외 경제 뉴스, 메모리 호황과 관련된 뉴스",
      "post_count": 6,
      "sentiment": "mixed",
      "urgency": "medium"
    }
  ],
  "keywords": [
    {
      "keyword": "이재명",
      "count": 3,
      "sentiment": "negative",
      "context": "방북 비용과 관련된 논란"
    },
    {
      "keyword": "애플",
      "count": 4,
      "sentiment": "neutral",
      "context": "애플페이 연동과 관련된 뉴스, 차단 모드 사용 중 스파이웨어 해킹 사례"
    },
    {
      "keyword": "경제",
      "count": 5,
      "sentiment": "mixed",
      "context": "국내외 경제 뉴스"
    }
  ],
  "sentiment_overview": {
    "positive": 10,
    "negative": 15,
    "neutral": 20,
    "overall_mood": "중립적이지만 약간 부정적인 기운이 감지됩니다."
  },
  "business_insights": [
    {
      "insight": "정치와 경제 뉴스가 많은 것으로 보아 최근 국내외 정세가 불안정한 것으로 보입니다.",
      "action": "시장 동향을 주시하고 대응策을 마련해야 합니다.",
      "priority": "high"
    },
    {
      "insight": "기술 뉴스가 많아 최근 기술 발전이 빠르다는 것을 알 수 있습니다.",
      "action": "신기술을 연구하고 투자해야 합니다.",
      "priority": "medium"
    }
  ],
  "narrative": "최근 국내외 정세가 불안정한 것으로 보이며, 기술 발전이 빠르다는 것을 알 수 있습니다. 따라서 시장 동향을 주시하고 대응책을 마련해야 하며, 신기술을 연구하고 투자해야 합니다. 또한, 최근 경제 뉴스가 많아 경제 동향을 주시해야 합니다.",
  "analyzed_at": "2026-03-29T19:30:34.124Z",
  "post_count": 62,
  "sources": [
    "ppomppu",
    "clien"
  ]
}