{
  "trending_topics": [
    {
      "topic": "정치",
      "summary": "이번 주에는 정치 관련된 글들이 많았습니다. 민주당의 김관영 전격 제명과 트럼프의 출생시민권 패소 전망 등이 주목을 받았습니다.",
      "post_count": 10,
      "sentiment": "negative",
      "urgency": "high"
    },
    {
      "topic": "경제",
      "summary": "경제 관련된 글들도 많았습니다. 주담대 상단 7% 돌파와 미 휘발유 가격 4달러 돌파 등이 주목을 받았습니다.",
      "post_count": 8,
      "sentiment": "negative",
      "urgency": "medium"
    },
    {
      "topic": "기술",
      "summary": "기술 관련된 글들도 많았습니다. 삼성전자와 하이닉스의 새로운 기술과 제품이 주목을 받았습니다.",
      "post_count": 12,
      "sentiment": "positive",
      "urgency": "low"
    }
  ],
  "keywords": [
    {
      "keyword": "트럼프",
      "count": 5,
      "sentiment": "negative",
      "context": "트럼프의 출생시민권 패소 전망"
    },
    {
      "keyword": "경제",
      "count": 8,
      "sentiment": "negative",
      "context": "주담대 상단 7% 돌파와 미 휘발유 가격 4달러 돌파"
    },
    {
      "keyword": "삼성전자",
      "count": 4,
      "sentiment": "positive",
      "context": "삼성전자와 하이닉스의 새로운 기술과 제품"
    }
  ],
  "sentiment_overview": {
    "positive": 15,
    "negative": 25,
    "neutral": 10,
    "overall_mood": "부정적인 기분이 대부분입니다."
  },
  "business_insights": [
    {
      "insight": "정치와 경제 관련된 글들이 많아졌습니다.",
      "action": "정치와 경제 관련된 마케팅 전략을 수립해야 합니다.",
      "priority": "high"
    },
    {
      "insight": "기술 관련된 글들이 많아졌습니다.",
      "action": "기술 관련된 마케팅 전략을 수립해야 합니다.",
      "priority": "medium"
    }
  ],
  "narrative": "이번 주에는 정치와 경제 관련된 글들이 많았습니다. 트럼프의 출생시민권 패소 전망과 주담대 상단 7% 돌파 등이 주목을 받았습니다. 기술 관련된 글들도 많았습니다. 삼성전자와 하이닉스의 새로운 기술과 제품이 주목을 받았습니다. 마케터들은 이러한 트렌드를 고려하여 마케팅 전략을 수립해야 합니다. 특히 정치와 경제 관련된 마케팅 전략을 수립해야 합니다. 또한 기술 관련된 마케팅 전략을 수립하여 새로운 기술과 제품을 홍보해야 합니다.",
  "analyzed_at": "2026-04-01T17:30:33.973Z",
  "post_count": 62,
  "sources": [
    "ppomppu",
    "clien"
  ]
}