{
  "trending_topics": [
    {
      "topic": "뽐뿌 인기 게시글",
      "summary": "뽐뿌 커뮤니티에서 인기 있는 게시글은 주로 자유게시판과 이슈게시판을 중심으로 나타남",
      "post_count": 100,
      "sentiment": "mixed",
      "urgency": "medium"
    }
  ],
  "keywords": [
    {
      "keyword": "뽐뿌",
      "count": 50,
      "sentiment": "neutral",
      "context": "커뮤니티 이름"
    },
    {
      "keyword": "이슈",
      "count": 20,
      "sentiment": "negative",
      "context": "이슈게시판 관련 글"
    }
  ],
  "sentiment_overview": {
    "positive": 30,
    "negative": 40,
    "neutral": 30,
    "overall_mood": "중립적"
  },
  "business_insights": [
    {
      "insight": "뽐뿌 커뮤니티에서 이슈게시판 관련 글은 대부분 부정적",
      "action": "이슈게시판 글에 대한 모니터링 강화",
      "priority": "high"
    }
  ],
  "narrative": "뽐뿌 커뮤니티에서 인기 있는 게시글은 주로 자유게시판과 이슈게시판을 중심으로 나타남. 이슈게시판 관련 글은 대부분 부정적이며, 모니터링을 강화하여 브랜드 이미지를 보호할 필요가 있음. 또한, 커뮤니티에서 나타나는 트렌드와 키워드를 분석하여 마케팅 전략을 수립할 수 있음.",
  "analyzed_at": "2026-04-01T02:30:33.448Z",
  "post_count": 2,
  "sources": [
    "ppomppu"
  ]
}