{
  "trending_topics": [
    {
      "topic": "트럼프의 이란 발전소 공격",
      "summary": "트럼프가 이란 발전소 공격을 예고하고 있으며, 이는 중동 전쟁의 가능성을 높인다. 이에 대한 우려와 비판이 커뮤니티에서 논의되고 있다.",
      "post_count": 5,
      "sentiment": "negative",
      "urgency": "high"
    },
    {
      "topic": "붉은 사막 게임",
      "summary": "붉은 사막 게임의 리뷰와 논란이 커뮤니티에서 चर्च되고 있다. 게임의 문제점과 개발사의 대응이 논의되고 있다.",
      "post_count": 3,
      "sentiment": "mixed",
      "urgency": "medium"
    },
    {
      "topic": "한국-프랑스 정상회담",
      "summary": "한국과 프랑스의 정상회담이 열렸으며, 이를 통해 양국 간의 협력과 이해가 강화될 것으로 기대된다.",
      "post_count": 2,
      "sentiment": "positive",
      "urgency": "medium"
    }
  ],
  "keywords": [
    {
      "keyword": "트럼프",
      "count": 7,
      "sentiment": "negative",
      "context": "이란 발전소 공격과 관련된 논란"
    },
    {
      "keyword": "붉은 사막",
      "count": 4,
      "sentiment": "mixed",
      "context": "게임의 리뷰와 논란"
    },
    {
      "keyword": "한국-프랑스 정상회담",
      "count": 2,
      "sentiment": "positive",
      "context": "양국 간의 협력과 이해 강화"
    }
  ],
  "sentiment_overview": {
    "positive": 10,
    "negative": 15,
    "neutral": 20,
    "overall_mood": "중립적인 분위기이지만, 일부 논란과 우려가 존재한다."
  },
  "business_insights": [
    {
      "insight": "중동 전쟁의 가능성이 높아짐에 따라 관련 산업의 동향을 주시해야 한다.",
      "action": "관련 산업의 동향을 분석하고, 사업 전략을 조정해야 한다.",
      "priority": "high"
    },
    {
      "insight": "게임 산업의 동향을 주시해야 한다.",
      "action": "게임 산업의 동향을 분석하고, 사업 전략을 조정해야 한다.",
      "priority": "medium"
    }
  ],
  "narrative": "현재 커뮤니티의 트렌드는 트럼프의 이란 발전소 공격과 관련된 논란, 붉은 사막 게임의 리뷰와 논란, 한국-프랑스 정상회담 등이다. 이러한 트렌드는 중동 전쟁의 가능성이 높아짐에 따라 관련 산업의 동향을 주시해야 하며, 게임 산업의 동향도 주시해야 한다. 또한, 커뮤니티의 분위기는 중립적인 분위기이지만, 일부 논란과 우려가 존재한다. 따라서, 관련 산업의 동향을 분석하고, 사업 전략을 조정해야 한다.",
  "analyzed_at": "2026-04-05T14:30:35.707Z",
  "post_count": 62,
  "sources": [
    "ppomppu",
    "clien"
  ]
}